[
  {
    "id": "25",
    "name": "Anaheim Ducks",
    "abbr": "ANA",
    "conference": "West",
    "division": "Pacific Division",
    "colors": [
      "#f47a38",
      "#b9975b",
      "#000000"
    ]
  },
  {
    "id": "1",
    "name": "Boston Bruins",
    "abbr": "BOS",
    "conference": "East",
    "division": "Atlantic Division",
    "colors": [
      "#ffb81c",
      "#000000",
      "#ffffff"
    ]
  },
  {
    "id": "2",
    "name": "Buffalo Sabres",
    "abbr": "BUF",
    "conference": "East",
    "division": "Atlantic Division",
    "colors": [
      "#002654",
      "#fcb514",
      "#c8102e"
    ]
  },
  {
    "id": "3",
    "name": "Calgary Flames",
    "abbr": "CGY",
    "conference": "West",
    "division": "Pacific Division",
    "colors": [
      "#c8102e",
      "#f1be48",
      "#000000"
    ]
  },
  {
    "id": "7",
    "name": "Carolina Hurricanes",
    "abbr": "CAR",
    "conference": "East",
    "division": "Metropolitan Division",
    "colors": [
      "#ce1126",
      "#000000",
      "#a4a9ad"
    ]
  },
  {
    "id": "4",
    "name": "Chicago Blackhawks",
    "abbr": "CHI",
    "conference": "West",
    "division": "Central Division",
    "colors": [
      "#cf0a2c",
      "#000000",
      "#ffd100"
    ]
  },
  {
    "id": "17",
    "name": "Colorado Avalanche",
    "abbr": "COL",
    "conference": "West",
    "division": "Central Division",
    "colors": [
      "#6f263d",
      "#236192",
      "#a2aaad"
    ]
  },
  {
    "id": "29",
    "name": "Columbus Blue Jackets",
    "abbr": "CBJ",
    "conference": "East",
    "division": "Metropolitan Division",
    "colors": [
      "#002654",
      "#ce1126",
      "#a4a9ad"
    ]
  },
  {
    "id": "9",
    "name": "Dallas Stars",
    "abbr": "DAL",
    "conference": "West",
    "division": "Central Division",
    "colors": [
      "#006847",
      "#8f8f8c",
      "#000000"
    ]
  },
  {
    "id": "5",
    "name": "Detroit Red Wings",
    "abbr": "DET",
    "conference": "East",
    "division": "Atlantic Division",
    "colors": [
      "#ce1126",
      "#ffffff",
      "#000000"
    ]
  },
  {
    "id": "6",
    "name": "Edmonton Oilers",
    "abbr": "EDM",
    "conference": "West",
    "division": "Pacific Division",
    "colors": [
      "#041e42",
      "#ff4c00",
      "#ffffff"
    ]
  },
  {
    "id": "26",
    "name": "Florida Panthers",
    "abbr": "FLA",
    "conference": "East",
    "division": "Atlantic Division",
    "colors": [
      "#c8102e",
      "#041e42",
      "#b9975b"
    ]
  },
  {
    "id": "8",
    "name": "Los Angeles Kings",
    "abbr": "LA",
    "conference": "West",
    "division": "Pacific Division",
    "colors": [
      "#111111",
      "#a2aaad",
      "#ffffff"
    ]
  },
  {
    "id": "30",
    "name": "Minnesota Wild",
    "abbr": "MIN",
    "conference": "West",
    "division": "Central Division",
    "colors": [
      "#154734",
      "#ddcba4",
      "#a6192e"
    ]
  },
  {
    "id": "10",
    "name": "Montreal Canadiens",
    "abbr": "MTL",
    "conference": "East",
    "division": "Atlantic Division",
    "colors": [
      "#af1e2d",
      "#192168",
      "#ffffff"
    ]
  },
  {
    "id": "27",
    "name": "Nashville Predators",
    "abbr": "NSH",
    "conference": "West",
    "division": "Central Division",
    "colors": [
      "#ffb81c",
      "#041e42",
      "#ffffff"
    ]
  },
  {
    "id": "11",
    "name": "New Jersey Devils",
    "abbr": "NJ",
    "conference": "East",
    "division": "Metropolitan Division",
    "colors": [
      "#ce1126",
      "#000000",
      "#ffffff"
    ]
  },
  {
    "id": "12",
    "name": "New York Islanders",
    "abbr": "NYI",
    "conference": "East",
    "division": "Metropolitan Division",
    "colors": [
      "#00539b",
      "#f47d30",
      "#ffffff"
    ]
  },
  {
    "id": "13",
    "name": "New York Rangers",
    "abbr": "NYR",
    "conference": "East",
    "division": "Metropolitan Division",
    "colors": [
      "#0038a8",
      "#ce1126",
      "#ffffff"
    ]
  },
  {
    "id": "14",
    "name": "Ottawa Senators",
    "abbr": "OTT",
    "conference": "East",
    "division": "Atlantic Division",
    "colors": [
      "#c8102e",
      "#000000",
      "#c2912c"
    ]
  },
  {
    "id": "15",
    "name": "Philadelphia Flyers",
    "abbr": "PHI",
    "conference": "East",
    "division": "Metropolitan Division",
    "colors": [
      "#f74902",
      "#000000",
      "#ffffff"
    ]
  },
  {
    "id": "16",
    "name": "Pittsburgh Penguins",
    "abbr": "PIT",
    "conference": "East",
    "division": "Metropolitan Division",
    "colors": [
      "#fcb514",
      "#000000",
      "#ffffff"
    ]
  },
  {
    "id": "18",
    "name": "San Jose Sharks",
    "abbr": "SJ",
    "conference": "West",
    "division": "Pacific Division",
    "colors": [
      "#006d75",
      "#ea7200",
      "#000000"
    ]
  },
  {
    "id": "124292",
    "name": "Seattle Kraken",
    "abbr": "SEA",
    "conference": "West",
    "division": "Pacific Division",
    "colors": [
      "#001628",
      "#99d9d9",
      "#355464"
    ]
  },
  {
    "id": "19",
    "name": "St. Louis Blues",
    "abbr": "STL",
    "conference": "West",
    "division": "Central Division",
    "colors": [
      "#002f87",
      "#fcb514",
      "#041e42"
    ]
  },
  {
    "id": "20",
    "name": "Tampa Bay Lightning",
    "abbr": "TB",
    "conference": "East",
    "division": "Atlantic Division",
    "colors": [
      "#002868",
      "#ffffff",
      "#000000"
    ]
  },
  {
    "id": "21",
    "name": "Toronto Maple Leafs",
    "abbr": "TOR",
    "conference": "East",
    "division": "Atlantic Division",
    "colors": [
      "#00205b",
      "#ffffff",
      "#000000"
    ]
  },
  {
    "id": "129764",
    "name": "Utah Mammoth",
    "abbr": "UTA",
    "conference": "West",
    "division": "Central Division",
    "colors": [
      "#71afe5",
      "#000000",
      "#ffffff"
    ]
  },
  {
    "id": "22",
    "name": "Vancouver Canucks",
    "abbr": "VAN",
    "conference": "West",
    "division": "Pacific Division",
    "colors": [
      "#001f5b",
      "#00843d",
      "#ffffff"
    ]
  },
  {
    "id": "37",
    "name": "Vegas Golden Knights",
    "abbr": "VGK",
    "conference": "West",
    "division": "Pacific Division",
    "colors": [
      "#333f42",
      "#b4975a",
      "#c8102e"
    ]
  },
  {
    "id": "23",
    "name": "Washington Capitals",
    "abbr": "WSH",
    "conference": "East",
    "division": "Metropolitan Division",
    "colors": [
      "#c8102e",
      "#041e42",
      "#ffffff"
    ]
  },
  {
    "id": "28",
    "name": "Winnipeg Jets",
    "abbr": "WPG",
    "conference": "West",
    "division": "Central Division",
    "colors": [
      "#041e42",
      "#004c97",
      "#ac162c"
    ]
  }
]
